{
    "libs": [
        // JavaScript only
        "es5",
        "es2015",
        "es2016",
        "es2017",
        "es2018",
        "es2019",
        "es2020",
        "esnext",
        // Host only
        "dom.generated",
        "dom.iterable.generated",
        "webworker.generated",
        "webworker.importscripts",
        "scripthost",
        // By-feature options
        "es2015.core",
        "es2015.collection",
        "es2015.generator",
        "es2015.iterable",
        "es2015.promise",
        "es2015.proxy",
        "es2015.reflect",
        "es2015.symbol",
        "es2015.symbol.wellknown",
        "es2016.array.include",
        "es2017.object",
        "es2017.sharedmemory",
        "es2017.string",
        "es2017.intl",
        "es2017.typedarrays",
        "es2018.asyncgenerator",
        "es2018.asynciterable",
        "es2018.regexp",
        "es2018.promise",
        "es2018.intl",
        "es2019.array",
        "es2019.object",
        "es2019.string",
        "es2019.symbol",
        "es2020.bigint",
        "es2020.promise",
        "es2020.string",
        "es2020.symbol.wellknown",
        "es2020.intl",
        "esnext.intl",
        "esnext.string",
        "esnext.promise",
        // Default libraries
        "es5.full",
        "es2015.full",
        "es2016.full",
        "es2017.full",
        "es2018.full",
        "es2019.full",
        "es2020.full",
        "esnext.full"
    ],
    "paths": {
        "dom.generated": "lib.dom.d.ts",
        "dom.iterable.generated": "lib.dom.iterable.d.ts",
        "webworker.generated": "lib.webworker.d.ts",
        "es5.full": "lib.d.ts",
        "es2015.full": "lib.es6.d.ts"
    }
}
